{"ol.epicgames.com":{"/":{"__cf_bm":{"key":"__cf_bm","value":"QsKW0ChfA6BDhchFqQerZO9uwkWj_UDp1W.UfBfipG4-1782957297.9333458-1.0.1.1-P0nQDZMFdxCAy.Y8qbSQwsJNuBwIEM6AWZ3bPMBGj0EJD1yFBtKIHL0QnZVq2ClEOwwp7ImRac2NqFrpWXSLnPHZWQZSqDh9bSj2mrsp425qxJlOJE.9nk7q_fVkWLRZ","expires":"2026-07-02T02:24:58.000Z","domain":"ol.epicgames.com","path":"/","secure":true,"httpOnly":true,"extensions":["SameSite=None"],"hostOnly":false,"creation":"2026-07-02T01:54:58.028Z","lastAccessed":"2026-07-02T01:54:58.028Z"}}}}